Workbook
Name NativeTimeline_Date: #N/A
Name Slicer_Payment_Method: #N/A
Name Slicer_Product_Name: #N/A
Name Slicer_Region: #N/A

Sheet Raw Data
A1: Transaction_ID | B1: Date | C1: Customer_ID | D1: Customer_Name | E1: Product_ID | F1: Product_Name | G1: Category | H1: Quantity | I1: Unit_Price | J1: Payment_Method | K1: Region | L1: Customer_Segment | M1: Customer_Since | N1: Total_Amount
A2: TRX0155 | B2: 45393 | C2: CUST023 | D2: Paul Baker | E2: P009 | F2: Monitor | G2: Electronics | H2: 3 | I2: 249.99 | J2: Cash | K2: Central | L2: Basic | M2: 44425 | N2: 749.97
A3: TRX0023 | B3: 45396 | C3: CUST013 | D3: Joseph Jackson | E3: P009 | F3: Monitor | G3: Electronics | H3: 3 | I3: 249.99 | J3: Credit Card | K3: Central | L3: Premium | M3: 44575 | N3: 749.97
A4: TRX0139 | B4: 45399 | C4: CUST021 | D4: Kevin Scott | E4: P005 | F4: Blender | G4: Appliances | H4: 3 | I4: 59.99 | J4: PayPal | K4: South | L4: Standard | M4: 45262 | N4: 179.97
A5: TRX0043 | B5: 45400 | C5: CUST046 | D5: Kathleen Bennett | E5: P005 | F5: Blender | G5: Appliances | H5: 3 | I5: 59.99 | J5: Cash | K5: North | L5: Premium | M5: 45114 | N5: 179.97
A6: TRX0212 | B6: 45400 | C6: CUST003 | D6: Michael Brown | E6: P008 | F6: Bookshelf | G6: Furniture | H6: 5 | I6: 149.99 | J6: Credit Card | K6: North | L6: Premium | M6: 45295 | N6: 749.95
A7: TRX0092 | B7: 45403 | C7: CUST024 | D7: Dorothy Nelson | E7: P005 | F7: Blender | G7: Appliances | H7: 2 | I7: 59.99 | J7: Cash | K7: West | L7: Standard | M7: 44746 | N7: 119.98
A8: TRX0193 | B8: 45403 | C8: CUST024 | D8: Dorothy Nelson | E8: P003 | F8: Headphones | G8: Electronics | H8: 5 | I8: 149.99 | J8: Credit Card | K8: Central | L8: Standard | M8: 44418 | N8: 749.95
A9: TRX0240 | B9: 45403 | C9: CUST017 | D9: Charles Allen | E9: P005 | F9: Blender | G9: Appliances | H9: 3 | I9: 59.99 | J9: Debit Card | K9: South | L9: Basic | M9: 45007 | N9: 179.97
A10: TRX0135 | B10: 45405 | C10: CUST009 | D10: Robert Thomas | E10: P001 | F10: Laptop | G10: Electronics | H10: 3 | I10: 899.99 | J10: PayPal | K10: East | L10: Standard | M10: 45299 | N10: 2699.97
A11: TRX0185 | B11: 45408 | C11: CUST026 | D11: Karen Hill | E11: P005 | F11: Blender | G11: Appliances | H11: 3 | I11: 59.99 | J11: Cash | K11: West | L11: Premium | M11: 45207 | N11: 179.97
A12: TRX0138 | B12: 45408 | C12: CUST022 | D12: Susan Green | E12: P008 | F12: Bookshelf | G12: Furniture | H12: 1 | I12: 149.99 | J12: Credit Card | K12: West | L12: Standard | M12: 45103 | N12: 149.99
A13: TRX0209 | B13: 45408 | C13: CUST046 | D13: Kathleen Bennett | E13: P008 | F13: Bookshelf | G13: Furniture | H13: 5 | I13: 149.99 | J13: Debit Card | K13: North | L13: Basic | M13: 44830 | N13: 749.95
... A251: TRX0064 | B251: 45758 | C251: CUST031 | D251: Steven Turner | E251: P010 | F251: Keyboard | G251: Electronics | H251: 3 | I251: 89.99 | J251: Debit Card | K251: North | L251: Premium | M251: 44878 | N251: 269.97

Sheet Task 1
A1: Customer Months | B1: Month End | C1: Today | D1: Current Date Time | E1: Customer Tenure
A2: 62 | B2: =EOMONTH(SalesData[[#This Row],[Date]],0) -> 45412 | C2: =TODAY() -> 46324 | D2: =NOW() -> 46324.385 | E2: =DATEDIF(SalesData[[#This Row],[Customer_Since]],C2,"Y") -> 5

Sheet Task 2
A1: FILTER – High Value Customers
A2: Customer Name | B2: Total Purchase
A3: {=_xlfn._xlws.FILTER('Raw Data'!D2:D201,'Raw Data'!N2:N201>1000,"No customers found")} -> Robert Thomas | B3: {=_xlfn._xlws.FILTER('Raw Data'!N2:N201,'Raw Data'!N2:N201>=1000,"")} -> 2699.97
A4: Michelle Rogers | B4: 2099.97
A5: Maria Garcia | B5: 1399.98
A6: Mark Carter | B6: 3599.96
A7: Barbara Young | B7: 3499.95
A8: Patricia Moore | B8: 2799.96
A9: Mark Carter | B9: 1199.96
A10: Nancy Collins | B10: 1249.95
A11: Susan Green | B11: 1499.95
A12: Jennifer Taylor | B12: 3499.95
A13: Joseph Jackson | B13: 1249.95
A14: Paul Baker | B14: 4499.95
A15: Edward Mitchell | B15: 4499.95
... A49: William White | B49: 3599.96

Sheet Task 3
A1: Total_Amount
A2: 749.97
A3: 749.97
A4: 179.97
A5: 179.97
A6: 749.95
A7: 119.98
A8: 749.95
A9: 179.97
A10: 2699.97
A11: 179.97
A12: 149.99
A13: 749.95
... A251: 269.97

Sheet Task 4
A1: Timestamp
A2: =IF(A2="","",IF(O2="",NOW(),O2)) -> 46324.385

Sheet Task 5
A1: Scenario | B1: Revenue | D1: Goal Seek Analysis
A2: Normal | B2: 229192.47 | D2: Current Average Sale | E2: =AVERAGE('[1]Raw Data'!H1:H250) -> 3.0120482
A3: High Sales | D3: Target Average Sale | E3: 1000
A4: Low Sales | D4: Required Unit Price | E4: =AVERAGE('Raw Data'!I2:I251) -> 296.67
A6: Average Transaction Amount | B6: 916.77 | D6: Goal Seek – Target Revenue
A7: Number of Transactions | B7: 272 | D7: Quantity | E7: 10
A8: Projected Revenue | B8: =B6*B7 -> 249361.44 | D8: Unit Price | E8: 500
D9: Expected Amount | E9: =E7*E8 -> 5000

Sheet Task 6
A1: SUMMARY OUTPUT
A3: Regression Statistics
A4: Multiple R | B4: 0.45808036
A5: R Square | B5: 0.20983762
A6: Adjusted R Square | B6: 0.20665148
A7: Standard Error | B7: 919.60715
A8: Observations | B8: 250
A10: ANOVA
B11: df | C11: SS | D11: MS | E11: F | F11: Significance F
A12: Regression | B12: 1 | C12: 55695917 | D12: 55695917 | E12: 65.859537 | F12: 2.2586479e-14
A13: Residual | B13: 248 | C13: 2.0972797e+08 | D13: 845677.32
A14: Total | B14: 249 | C14: 2.6542389e+08
B16: Coefficients | C16: Standard Error | D16: t Stat | E16: P-value | F16: Lower 95% | G16: Upper 95% | H16: Lower 95.0% | I16: Upper 95.0%
A17: Intercept | B17: -148.85465 | C17: 143.61334 | D17: -1.0364959 | E17: 0.3009804 | F17: -431.712 | G17: 134.0027 | H17: -431.712 | I17: 134.0027
A18: Quantity | B18: 353.793 | C18: 43.595323 | D18: 8.1153889 | E18: 2.2586479e-14 | F18: 267.92872 | G18: 439.65729 | H18: 267.92872 | I18: 439.65729

Sheet Task 7
A1: Sales Performance Analysis
A3: Month | B3: Monthly Revenue | D3: Region Analysis | E3: Column1
A4: 45383 | B4: =SUMIFS(SalesData[Total_Amount],SalesData[Date],">="&A4,SalesData[Date],"<"&EDATE(A4,1)) -> 20919.33 | D4: Region | E4: Total Revenue
A5: 45413 | B5: =SUMIFS(SalesData[Total_Amount],SalesData[Date],">="&A5,SalesData[Date],"<"&EDATE(A5,1)) -> 17039.35 | D5: East | E5: =SUMIF(SalesData[Region],D5,SalesData[Total_Amount]) -> 59288.39
A6: 45444 | B6: =SUMIFS(SalesData[Total_Amount],SalesData[Date],">="&A6,SalesData[Date],"<"&EDATE(A6,1)) -> 19299.45 | D6: North | E6: =SUMIF(SalesData[Region],D6,SalesData[Total_Amount]) -> 50808.31
A7: 45474 | B7: =SUMIFS(SalesData[Total_Amount],SalesData[Date],">="&A7,SalesData[Date],"<"&EDATE(A7,1)) -> 18479.4 | D7: West | E7: =SUMIF(SalesData[Region],D7,SalesData[Total_Amount]) -> 41408.68
A8: 45505 | B8: =SUMIFS(SalesData[Total_Amount],SalesData[Date],">="&A8,SalesData[Date],"<"&EDATE(A8,1)) -> 15759.43 | D8: South | E8: =SUMIF(SalesData[Region],D8,SalesData[Total_Amount]) -> 36398.75
A9: 45536 | B9: =SUMIFS(SalesData[Total_Amount],SalesData[Date],">="&A9,SalesData[Date],"<"&EDATE(A9,1)) -> 12989.51
A10: 45566 | B10: =SUMIFS(SalesData[Total_Amount],SalesData[Date],">="&A10,SalesData[Date],"<"&EDATE(A10,1)) -> 20609.52
A11: 45597 | B11: =SUMIFS(SalesData[Total_Amount],SalesData[Date],">="&A11,SalesData[Date],"<"&EDATE(A11,1)) -> 12309.44
A12: 45627 | B12: =SUMIFS(SalesData[Total_Amount],SalesData[Date],">="&A12,SalesData[Date],"<"&EDATE(A12,1)) -> 23039.3
A13: 45658 | B13: =SUMIFS(SalesData[Total_Amount],SalesData[Date],">="&A13,SalesData[Date],"<"&EDATE(A13,1)) -> 25799.15
A14: 45689 | B14: =SUMIFS(SalesData[Total_Amount],SalesData[Date],">="&A14,SalesData[Date],"<"&EDATE(A14,1)) -> 16069.38
A15: 45717 | B15: =SUMIFS(SalesData[Total_Amount],SalesData[Date],">="&A15,SalesData[Date],"<"&EDATE(A15,1)) -> 19899.38
A16: 45748 | B16: =SUMIFS(SalesData[Total_Amount],SalesData[Date],">="&A16,SalesData[Date],"<"&EDATE(A16,1)) -> 6979.83

Sheet Task 8
A1: High-Value Customers | B1: Column1
A2: Customer ID | B2: Total Amount
A3: CUST025 | B3: =SUMIF(SalesData[Customer_ID],A3,SalesData[Total_Amount]) -> 15659.65
A5: Product Analysis | B5: Column1
A6: Product Name | B6: Total Revenue
A7: Laptop | B7: =SUMIF(SalesData[Product_Name],A7,SalesData[Total_Amount]) -> 67499.25
A8: Smartphone | B8: =SUMIF(SalesData[Product_Name],A8,SalesData[Total_Amount]) -> 67199.04
A9: Bookshelf | B9: =SUMIF(SalesData[Product_Name],A9,SalesData[Total_Amount]) -> 15298.98
A10: Monitor | B10: =SUMIF(SalesData[Product_Name],A10,SalesData[Total_Amount]) -> 21999.12

Sheet Task 9
A1: Most Frequently Purchased Product
A2: Product Name | B2: Purchase Count | C2: Total Quantity
A3: {=_xlfn.UNIQUE('Raw Data'!F2:F251)} -> Monitor | B3: =COUNTIF('Raw Data'!F:F,A3) -> 26 | C3: =SUMIF('Raw Data'!F:F,A3,'Raw Data'!H:H) -> 88
A4: Blender | B4: =COUNTIF('Raw Data'!F:F,A4) -> 29 | C4: =SUMIF('Raw Data'!F:F,A4,'Raw Data'!H:H) -> 87
A5: Bookshelf | B5: =COUNTIF('Raw Data'!F:F,A5) -> 35 | C5: =SUMIF('Raw Data'!F:F,A5,'Raw Data'!H:H) -> 102
A6: Headphones | B6: =COUNTIF('Raw Data'!F:F,A6) -> 16 | C6: =SUMIF('Raw Data'!F:F,A6,'Raw Data'!H:H) -> 47
A7: Laptop | B7: =COUNTIF('Raw Data'!F:F,A7) -> 24 | C7: =SUMIF('Raw Data'!F:F,A7,'Raw Data'!H:H) -> 75
A8: Smartphone | B8: =COUNTIF('Raw Data'!F:F,A8) -> 31 | C8: =SUMIF('Raw Data'!F:F,A8,'Raw Data'!H:H) -> 96
A9: Desk | B9: =COUNTIF('Raw Data'!F:F,A9) -> 26 | C9: =SUMIF('Raw Data'!F:F,A9,'Raw Data'!H:H) -> 78
A10: Coffee Maker | B10: =COUNTIF('Raw Data'!F:F,A10) -> 14 | C10: =SUMIF('Raw Data'!F:F,A10,'Raw Data'!H:H) -> 39
A11: Keyboard | B11: =COUNTIF('Raw Data'!F:F,A11) -> 34 | C11: =SUMIF('Raw Data'!F:F,A11,'Raw Data'!H:H) -> 89
A12: Office Chair | B12: =COUNTIF('Raw Data'!F:F,A12) -> 15 | C12: =SUMIF('Raw Data'!F:F,A12,'Raw Data'!H:H) -> 52

Sheet Task 10
A1: Compare Two Lists
A2: List 1 | B2: List 2 | C2: Matching Names
A3: Paul Baker | B3: Karen Hill | C3: {=_xlfn._xlws.FILTER(A3:A11,COUNTIF(B3:B11,A3:A11)>0,"No Matching Names")} -> Kathleen Bennett
A4: Joseph Jackson | B4: Susan Green
A5: Kevin Scott | B5: Kathleen Bennett
A6: Kathleen Bennett | B6: Peter Richardson
A7: Michael Brown | B7: Dennis Gray
A8: Dorothy Nelson | B8: Michelle Rogers
A9: Dorothy Nelson | B9: George Adams
A10: Charles Allen | B10: Mark Carter
A11: Robert Thomas | B11: Maria Garcia

Sheet Task 11
A1: Abbreviations
A2: Customer Name | B2: Abbreviation
A3: ='Raw Data'!D2 -> Paul Baker | B3: =UPPER(LEFT(A3,1)&MID(A3,FIND(" ",A3)+1,1)) -> PB
A4: ='Raw Data'!D3 -> Joseph Jackson | B4: =UPPER(LEFT(A4,1)&MID(A4,FIND(" ",A4)+1,1)) -> JJ
A5: ='Raw Data'!D4 -> Kevin Scott | B5: =UPPER(LEFT(A5,1)&MID(A5,FIND(" ",A5)+1,1)) -> KS
A6: ='Raw Data'!D5 -> Kathleen Bennett | B6: =UPPER(LEFT(A6,1)&MID(A6,FIND(" ",A6)+1,1)) -> KB
A7: ='Raw Data'!D6 -> Michael Brown | B7: =UPPER(LEFT(A7,1)&MID(A7,FIND(" ",A7)+1,1)) -> MB
A8: ='Raw Data'!D7 -> Dorothy Nelson | B8: =UPPER(LEFT(A8,1)&MID(A8,FIND(" ",A8)+1,1)) -> DN
A9: ='Raw Data'!D8 -> Dorothy Nelson | B9: =UPPER(LEFT(A9,1)&MID(A9,FIND(" ",A9)+1,1)) -> DN
A10: ='Raw Data'!D9 -> Charles Allen | B10: =UPPER(LEFT(A10,1)&MID(A10,FIND(" ",A10)+1,1)) -> CA
A11: ='Raw Data'!D10 -> Robert Thomas | B11: =UPPER(LEFT(A11,1)&MID(A11,FIND(" ",A11)+1,1)) -> RT
A12: ='Raw Data'!D11 -> Karen Hill | B12: =UPPER(LEFT(A12,1)&MID(A12,FIND(" ",A12)+1,1)) -> KH
A13: ='Raw Data'!D12 -> Susan Green | B13: =UPPER(LEFT(A13,1)&MID(A13,FIND(" ",A13)+1,1)) -> SG
A14: ='Raw Data'!D13 -> Kathleen Bennett | B14: =UPPER(LEFT(A14,1)&MID(A14,FIND(" ",A14)+1,1)) -> KB
A15: ='Raw Data'!D14 -> Peter Richardson | B15: =UPPER(LEFT(A15,1)&MID(A15,FIND(" ",A15)+1,1)) -> PR

Sheet Dashboard Task 12
A1: Sales Performance Dashboard
B2: Total Revenue | D2: Total Transactions | F2: Total Quantity | H2: Total Customers
B3: =SUM(SalesData[Total_Amount]) -> 229192.47 | D3: =COUNTA(SalesData[Transaction_ID]) -> 250 | F3: =SUM(SalesData[Quantity]) -> 753 | H3: =COUNTA(_xlfn.UNIQUE(SalesData[Customer_ID])) -> 50
G4: 1

Sheet Task 13
A1: FINAL SALES REPORT — INSIGHTS & STORYTELLING
A2: Sales performance review based on 250 transactions and 50 customers
A4: Total Revenue | C4: Transactions | E4: Units Sold
A5: ₹229,192.47 | C5: 250 | E5: 753
A6: Customers | C6: Avg Transaction | E6: Avg Basket
A7: 50 | C7: ₹916.77 | E7: 3.01 units
A9: EXECUTIVE STORY
A10: The business generated ₹229,192.47 from 250 transactions, selling 753 units to 50 customers. Revenue is concentrated in premium electronics: laptops and smartphones together generated ₹134,698.29, or 58.7% of total revenue. The strongest market was East, while the largest customer was CUST025. The opportunity is to protect the electronics core, retain high-value customers, and use volume products for cross-selling.
A14: KEY INSIGHTS
A15: Product concentration | B15: Laptop revenue was ₹67,499.25 and smartphone revenue was ₹67,199.04. Together they account for approximately 58.7% of sales.
A16: Regional performance | B16: East led with ₹59,288.39, followed by North at ₹50,808.31. South was lowest at ₹36,398.75.
A17: Customer concentration | B17: CUST025 was the highest-value customer at ₹15,659.65, representing approximately 6.8% of total revenue.
A18: Seasonality | B18: January 2025 was the strongest month at ₹25,799.15; April 2025 was the weakest at ₹6,979.83.
A19: Volume opportunity | B19: Bookshelf led purchase frequency with 35 purchases and 102 units, making it a useful cross-selling product.
A22: RECOMMENDED ACTIONS
A23: 1. | B23: Protect laptop and smartphone inventory and visibility.
A24: 2. | B24: Create bundles: laptops with keyboards, monitors, headphones, or office chairs.
A25: 3. | B25: Launch VIP retention offers for CUST025 and other repeat high-value customers.
A26: 4. | B26: Replicate East-region tactics in North and West; investigate the South-region gap.
A27: 5. | B27: Plan targeted promotions before April-type slowdowns and track monthly performance.
A30: MANAGEMENT TAKEAWAY
A31: The company has a strong premium-product engine, but performance is concentrated. Sustainable growth will come from combining reliable electronics availability with customer retention, regional expansion, seasonal planning, and cross-selling.

Sheet Pivot Table
A3: Sum of Total_Amount | B3: Count of Customer_ID | C3: Sum of Quantity | D3: Count of Transaction_ID
A4: 229192.47 | B4: 250 | C4: 753 | D4: 250
